webmage/__init__.py
webmage/rune.py
webmage/rune_list.py
webmage/spell.py
webmage/support.py
webmage-1.0.3.dist-info/LICENSE
webmage-1.0.3.dist-info/METADATA
webmage-1.0.3.dist-info/WHEEL
webmage-1.0.3.dist-info/top_level.txt
webmage-1.0.3.dist-info/RECORD
