Metadata-Version: 2.1
Name: webmage
Version: 1.0.3
Summary: A library with built-in methods that make web scraping easier for dynamically loading pages.
Home-page: https://github.com/javascriptorian/webmage
Author: The JavaScriptorian
Author-email: javascriptorian@gmail.com
Classifier: Programming Language :: Python :: 3
Classifier: License :: OSI Approved :: MIT License
Classifier: Operating System :: OS Independent
Requires-Python: >=3.9
License-File: LICENSE
Requires-Dist: webdriver-manager >=3.8.5
Requires-Dist: selenium >=4.8.2
Requires-Dist: beautifulsoup4 >=4.11.2
Requires-Dist: undetected-chromedriver >=3.4.6
